AUTHORS.rst
CHANGES.rst
CITATION.cff
LICENSE.rst
MANIFEST.in
README.rst
pyproject.toml
setup.cfg
setup.py
src/plume/__init__.py
src/plume/_version.py
src/plume/centerline.py
src/plume/cli.py
src/plume/plume.py
src/plume/river.py
src/plume/ext/__init__.py
src/plume/ext/centerline.pyx
src/sed_plume.egg-info/PKG-INFO
src/sed_plume.egg-info/SOURCES.txt
src/sed_plume.egg-info/dependency_links.txt
src/sed_plume.egg-info/entry_points.txt
src/sed_plume.egg-info/requires.txt
src/sed_plume.egg-info/top_level.txt
tests/__init__.py
tests/test_centerline.py
tests/test_cli.py
tests/test_plume.py