Metadata-Version: 2.1
Name: sed-plume
Version: 0.2.2
Summary: A hypopycnal sediment-carrying plume entering the ocean.
Author: Eric Hutton
Author-email: mcflugen@gmail.com
Maintainer: Eric Hutton
Maintainer-email: mcflugen@gmail.com
License: The MIT License (MIT)
Project-URL: homepage, https://github.com/csdms
Project-URL: documentation, https://github.com/mcflugen/plume/blob/main/README.rst
Project-URL: repository, https://github.com/mflugen/plume
Project-URL: changelog, https://github.com/mcflugen/plume/blob/main/CHANGES.rst
Keywords: bmi,landlab,sediment,hypopycnal plume
Classifier: Development Status :: 4 - Beta
Classifier: Intended Audience :: Science/Research
Classifier: License :: OSI Approved :: MIT License
Classifier: Operating System :: OS Independent
Classifier: Programming Language :: Cython
Classifier: Programming Language :: Python :: 3
Classifier: Programming Language :: Python :: 3.9
Classifier: Programming Language :: Python :: 3.10
Classifier: Programming Language :: Python :: 3.11
Classifier: Programming Language :: Python :: Implementation :: CPython
Classifier: Topic :: Scientific/Engineering :: Physics
Requires-Python: >=3.9
License-File: LICENSE.rst
License-File: AUTHORS.rst
Requires-Dist: landlab>=2.0.0b7
Requires-Dist: numpy
Requires-Dist: pyyaml
Requires-Dist: rich-click
Requires-Dist: scipy
Requires-Dist: tomlkit
Provides-Extra: dev
Requires-Dist: black; extra == "dev"
Requires-Dist: flake8; extra == "dev"
Requires-Dist: flake8-bugbear; extra == "dev"
Requires-Dist: isort; extra == "dev"
Requires-Dist: pre-commit; extra == "dev"
Provides-Extra: testing
Requires-Dist: coveralls; extra == "testing"
Requires-Dist: hypothesis; extra == "testing"
Requires-Dist: nbmake; extra == "testing"
Requires-Dist: pytest; extra == "testing"
Requires-Dist: pytest-cov; extra == "testing"
Requires-Dist: pytest-datadir; extra == "testing"
Requires-Dist: pytest-xdist; extra == "testing"
Requires-Dist: pyyaml; extra == "testing"
Provides-Extra: notebook
Requires-Dist: notebook; extra == "notebook"
